mkdocs_document_dates/__init__.py
mkdocs_document_dates/hooks_installer.py
mkdocs_document_dates/plugin.py
mkdocs_document_dates/styles.py
mkdocs_document_dates/hooks/pre-commit
mkdocs_document_dates/lang/__init__.py
mkdocs_document_dates/lang/ar.py
mkdocs_document_dates/lang/de.py
mkdocs_document_dates/lang/en.py
mkdocs_document_dates/lang/es.py
mkdocs_document_dates/lang/fr.py
mkdocs_document_dates/lang/ja.py
mkdocs_document_dates/lang/ko.py
mkdocs_document_dates/lang/ru.py
mkdocs_document_dates/lang/zh.py
mkdocs_document_dates/lang/zh_tw.py
mkdocs_document_dates-2.0.0.dist-info/LICENSE
mkdocs_document_dates-2.0.0.dist-info/METADATA
mkdocs_document_dates-2.0.0.dist-info/WHEEL
mkdocs_document_dates-2.0.0.dist-info/entry_points.txt
mkdocs_document_dates-2.0.0.dist-info/top_level.txt
mkdocs_document_dates-2.0.0.dist-info/RECORD
