Metadata-Version: 2.2
Name: mkdocs-document-dates
Version: 2.0.0
Summary: A MkDocs plugin for displaying accurate document creation and last modification dates.
Home-page: https://github.com/jaywhj/mkdocs-document-dates
Author: Aaron Wang
Classifier: Programming Language :: Python :: 3
Classifier: License :: OSI Approved :: MIT License
Classifier: Operating System :: OS Independent
Requires-Python: >=3.6
License-File: LICENSE
Requires-Dist: mkdocs>=1.0.0
Dynamic: author
Dynamic: classifier
Dynamic: description
Dynamic: description-content-type
Dynamic: home-page
Dynamic: requires-dist
Dynamic: requires-python
Dynamic: summary
